<?xml version = '1.0' encoding = 'UTF-8'?>
<Diagram class="oracle.dbtools.crest.swingui.relational.DPVRelationalSubView" name="From_LM_Logical - SubView_1" id="08FDBED7-F855-5741-659A-CBD466BADB60">
<createdBy>mario</createdBy>
<modifiedBy>mario</modifiedBy>
<createdTime>2016-03-29 23:05:48 UTC</createdTime>
<autoRoute>false</autoRoute>
<boxInbox>true</boxInbox>
<showLegend>false</showLegend>
<showLabels>false</showLabels>
<showRelAttributes>false</showRelAttributes>
<gridEnabled>false</gridEnabled>
<showGrid>false</showGrid>
<diagramColor>-1</diagramColor>
<display>false</display>
<generatorId>FFFC7696-22AA-4B81-E1CB-E9E5F4301FE7</generatorId>
<notation>1</notation>
</Diagram>